pycommonlib/__init__.py
pycommonlib/ali/__init__.py
pycommonlib/ali/exceptions.py
pycommonlib/ali/message_queue.py
pycommonlib/ali/mns/__init__.py
pycommonlib/ali/mns/http_client.py
pycommonlib/ali/mns/queue.py
pycommonlib/ali/mns/xml_helper.py
pycommonlib/ali/sms/__init__.py
pycommonlib/ali/sms/sms_client.py
pycommonlib/django/__init__.py
pycommonlib/django/middleware/__init__.py
pycommonlib/django/middleware/crossdomainaccess.py
pycommonlib/django/util/__init__.py
pycommonlib/django/util/ipaddress.py
pycommonlib/jpush/__init__.py
pycommonlib/jpush/jpush_lib.py
pycommonlib/rest_framework/__init__.py
pycommonlib/rest_framework/authentication.py
pycommonlib/rest_framework/decorators.py
pycommonlib/rest_framework/renders.py
pycommonlib/rest_framework_xml/__init__.py
pycommonlib/rest_framework_xml/parsers.py
pycommonlib/util/TaskScheduler.py
pycommonlib/util/__init__.py
pycommonlib/util/cache.py
pycommonlib/util/datetime.py
pycommonlib/util/db_helper.py
pycommonlib/util/file.py
pycommonlib/util/module_helper.py
pycommonlib/util/obj_helper.py
pycommonlib/util/random_helper.py
pycommonlib/weixin/__init__.py
pycommonlib/weixin/exceptions.py
pycommonlib/weixin/weixin_lib.py
pycommonlib-1.0.30.dist-info/DESCRIPTION.rst
pycommonlib-1.0.30.dist-info/METADATA
pycommonlib-1.0.30.dist-info/RECORD
pycommonlib-1.0.30.dist-info/WHEEL
pycommonlib-1.0.30.dist-info/metadata.json
pycommonlib-1.0.30.dist-info/top_level.txt
